FHEMP/__init__.py
FHEMP/core.py
FHEMP/interface.py
FHEMP/test.py
fhemp-0.6.0.dist-info/licenses/LICENSE.txt
fhemp-0.6.0.dist-info/METADATA
fhemp-0.6.0.dist-info/WHEEL
fhemp-0.6.0.dist-info/top_level.txt
fhemp-0.6.0.dist-info/RECORD
