Metadata-Version: 2.4
Name: FHEMP
Version: 0.6.0
Summary: Гомоморфное шифрование на основе матричных полиномов
Author: EvZait
License: MIT
Requires-Python: >=3.8
License-File: LICENSE.txt
Requires-Dist: numpy
Dynamic: author
Dynamic: description
Dynamic: description-content-type
Dynamic: license
Dynamic: license-file
Dynamic: requires-dist
Dynamic: requires-python
Dynamic: summary
